full_calendar_component/FullCalendarComponent.py
full_calendar_component/__init__.py
full_calendar_component/_imports_.py
full_calendar_component/full_calendar_component.min.js
full_calendar_component/full_calendar_component.min.js.map
full_calendar_component/metadata.json
full_calendar_component/package-info.json
full_calendar_component-0.0.4.dist-info/LICENSE
full_calendar_component-0.0.4.dist-info/METADATA
full_calendar_component-0.0.4.dist-info/WHEEL
full_calendar_component-0.0.4.dist-info/top_level.txt
full_calendar_component-0.0.4.dist-info/RECORD
