Metadata-Version: 2.1
Name: full-calendar-component
Version: 0.0.4
Summary: fullcalendar.io component for Dash
Author: Pip Install Python <pipinstallpython@gmail.com>
License: MIT
Classifier: Framework :: Dash
License-File: LICENSE
